{
  "basics": {
    "name": "Angelina Abitino",
    "label": "Student",
    "picture": "https://angelina-abitino.github.io/images/profile_small.jpg",
    "email": "angelina.abitino@gmail.com",
    "phone": "",
    "website": "https://angelina-abitino.github.io",
    "summary": "I am an engineer interested in the advancement of safe and equitable machine learning systems. When I'm not coding you might find me cooking, making pottery, or taking pictures of the people and places around me. Click the tumblr link below for a look at my photography portfolio.",
    "location": {
      "address": "",
      "postalCode": "",
      "city": "Madison",
      "countryCode": "",
      "region": "Wisconsin"
    },
    "profiles": [
      {
        "network": "github",
        "username": "angelina-abitino",
        "url": "http://github.com/angelina-abitino"
      },
      {
        "network": "linkedin",
        "username": "angelinaabitino",
        "url": "http://linkedin.com/in/angelinaabitino"
      },
      {
        "network": "tumblr",
        "username": "picturesaswords",
        "url": "http://picturesaswords.tumblr.com"
      }
    ]
  },
  "interests": [
    {
      "name": "software engineering",
      "keywords": [
      ]
    },
    {
      "name": "machine learning",
      "keywords": [
      ]
    },
    {
      "name": "computer vision",
      "keywords": [
      ]
    },
    {
      "name": "artificial intelligence",
      "keywords": [
      ]
    },
    {
      "name": "photography",
      "keywords": [
      ]
    },
    {
      "name": "ceramics",
      "keywords": [
      ]
    },
    {
      "name": "violin",
      "keywords": [
      ]
    },
    {
      "name": "food",
      "keywords": [
      ]
    },
    {
      "name": "travel",
      "keywords": [
      ]
    },
    {
      "name": "sustainability",
      "keywords": [
      ]
    }
  ],
  "skills": [
    {
      "name": "Languages and Frameworks",
      "level": "",
      "keywords": [
        "Python",
        "TensorFlow",
        "Keras",
        "TFLearn",
        "Sci-Kit Learn",
        "SQL",
        "C++",
        "C",
        "JavaScript",
        "HTML/CSS",
        "React",
        "Matlab"
      ]
    },
    {
      "name": "Toolsets/OS",
      "level": "",
      "keywords": [
        "MacOS",
        "Linux",
        "Windows",
        "Git/GitHub",
        "gnu tools",
        "microcontrollers",
        "TI LaunchPad"
      ]
    }
  ],
  "education": [
    {
      "institution": "Swarthmore College, Swarthmore, PA",
      "area": "Engineering and Computer Science (expected Spring, 2018)",
      "studyType": "B.S.",
      "startDate": "2014-09-01",
      "endDate": "2018-05-22",
      "gpa": "",
      "courses": [
      ]
    }
  ],
  "work": [
    {
      "company": "Epic",
      "position": "Integration Engineer - Data Aggregation",
      "website": "",
      "startDate": "2018-08-01",
      "endDate": "present",
      "summary": "",
      "highlights": [
        "Developed extraction, transformation, and load processes to import large scale claims data into SQL server databases",
        "Designed queries to validate data in non-production environments",
        "Streamlined and managed claims import projects for healthcare organizations"
      ]
    },
    {
      "company": "Rochester Institute of Technology",
      "position": "Student Researcher",
      "website": "",
      "startDate": "2017-06-01",
      "endDate": "2017-08-11",
      "summary": "",
      "highlights": [
        "Awarded grant from National Science Foundation to engage in lifelong learning research for Research Experiences for Undergraduates",
        "Conducted systematic literature review on proposed methods to reduce catastrophic forgetting in deep neural networks",
        "Designed and implemented experiments to evaluate and compare mitigation methods with Python using Keras, and Tensorflow libraries",
        "Co-authored paper accepted into 2018 Conference on Artificial Intelligence"  
      ]
    },
    {
      "company": "Swarthmore College Office of Student Engagement",
      "position": "Resident Assistant",
      "website": "",
      "startDate": "2017-08-01",
      "endDate": "2018-05-22",
      "summary": "",
      "highlights": [
        "Responsible for a dormitory housing 48 students",
        "General resource and counselor for the student body",
        "Liaison between students and the administration"
      ]
    },
    {
      "company": "Swarthmore College Communications Department",
      "position": "Photographer",
      "website": "",
      "startDate": "2015-09-01",
      "endDate": "2018-05-22",
      "summary": "",
      "highlights": [
        "Photographed campus events and edited media for official college social media and quarterly publication, the Swarthmore College Bulletin"
      ]
    },
    {
      "company": "Swarthmore College Engineering Department",
      "position": "Teaching Assistant",
      "website": "",
      "startDate": "2017-09-01",
      "endDate": "2017-12-22",
      "summary": "",
      "highlights": [
        "Graded coursework for Digital Systems and Computer Engineering Fundamentals, as well as Design of Digital and Embedded Systems"
      ]
    }
  ],
  "publications": [
    {
      "name": "Measuring Catastrophic Forgetting in Neural Networks",
      "type": "conference",
      "author": "Kemker, R., McClure, M., Abitino, A., Hayes, T., Kanan, C. ",
      "publisher": "Association for the Advancement of Artificial Intelligence 2018",
      "releaseDate": "January, 2018",
      "website": "https://aaai.org/ocs/index.php/AAAI/AAAI18/paper/view/16410",
      "summary": ""
    },
   ],
  "references": [
    {
      "name": "Available upon request",
      "reference": ""
    }
  ]
}
